{
  "Birth name": [{ "Jada Koren Pinkett": "1110000" }],
  "Also known as": [
    { "The Bloody Brothers": "1010000" },
    { "Inearthed (1993 - 1997)": "0010000" }
  ],
  "Born": [
    {
      "December 23, 1929 ( 1929-12-23 )  Yale, Oklahoma, United States": "0010000"
    }
  ],
  "Genres": [{ "Rock": "0000000" }, { "Rock ": "0110000" }],
  "Occupation(s)": [
    { "Songwriter": "1110000" },
    { "author": "0111000" },
    { "Actress": "1111000" }
  ],
  "Instruments": [{ "Vocals": "0000000" }, { "piano": "1010000" }],
  "Years active": [{ "1963-present": "0000000" }],
  "Labels": [
    { "United Artists": "0000000" },
    { "Spin": "1110000" },
    { "Capitol": "0110000" },
    { "Visible Noise ": "0010000" },
    { " Rhino/Atlantic": "0010000" },
    { "Brunswick": "1110000" },
    { "Atlantic": "1010000" }
  ],
  "Associated acts": [
    { "Bad Boy": "1010000" },
    { "Ice Cube": "1010000" },
    { "Fire Deuce": "1010000" },
    { "The Idle Race": "0000000" },
    { "Markiplier": "1110000" },
    { "Legion of Mary": "1010000" },
    { "Nicki Minaj": "0110000" }
  ],
  "Website": [{ "Official website": "0110000" }],
  "title": ["Jeff Lynne"]
}
