{
  "Capital": [{ "Manila  a": "0010000" }],
  "Largest city": [{ "Bujumbura": "0010000" }],
  "Official language and national language": [{ "Korean": "1111000" }],
  "Regional languages": [{ "Spanish": "0111000" }],
  "Ethnic groups": [{ "4% Other (including Shona and Kgalagadi)": "0010000" }],
  "Religion": [
    { "Roman Catholicism": "1110000" },
    { "Church of England": "1010000" },
    { "Christianity ( Church of England )": "1010000" },
    { "Anglican": "1110000" },
    { "Church of Iceland": "1010000" },
    { "0.7% Buddhism": "0000000" },
    { "Church of the Faroe Islands": "0010000" }
  ],
  "Demonym(s)": [{ "Tico(a)": "1010000" }],
  "Government": [{ "Presidential republic": "0010000" }],
  "President": [{ "Sarvepalli Radhakrishnan (1980-1984) (2)": "1110000" }],
  "Vice President": [
    {
      "Gianpietro Benedetti, Chairman , Giacomo Mareschi Danieli, CEO , Alessandro Trivillin, CEO": "1111000"
    }
  ],
  "DPR Speaker": [{ "Dr. Alison Elliot, General Secretary": "0111000" }],
  "Chief Justice": [{ "Katsuo Ono": "1111000" }],
  "Legislature": [{ "National Assembly": "0010000" }],
  "Upper house": [{ "Regional Representative Council (DPD)": "0000000" }],
  "Lower house": [{ "People's Representative Council (DPR)": "0000000" }],
  "title": ["Republic of Indonesia  (Republik Indonesia (Indonesian))"]
}
