{
  "Island": [{ "South Island": "0000000" }],
  "Region": [{ "London": "0110000" }],
  "Territorial authority": [{ "Christchurch City Council": "0000000" }],
  "Wards": [
    { "Broad Street": "0110000" },
    { "Funchal, Madeira, Portugal": "0111000" },
    { "101": "1010000" },
    { "Central ": "0000000" },
    { "Coastal ": "0000000" },
    { "Fendalton ": "0000000" },
    { "Halswell ": "0000000" },
    { "Bujumbura": "0111000" },
    { "Heathcote ": "0000000" },
    { "Manacor, Mallorca, Spain": "1111000" },
    { "Tegucigalpa": "1111000" },
    { "Florida City , Everglades City": "1111000" },
    { "Papanui ": "0000000" },
    { "101": "1010000" },
    { "Cameron, North Carolina": "0111000" },
    { "Billingsgate": "0110000" }
  ],
  "Settled by the UK": [{ "10 December 1898": "0111000" }],
  "Named for": [{ "Christopher Columbus": "0010000" }],
  "title": ["Christchurch  (Otautahi   (Maori))"]
}
