{
  "Born": [
    {
      "(1947-07-19) 19 July 1947 (age 71) , Hampton, London, England": "0110000"
    }
  ],
  "Residence": [
    { "Pacific Palisades, Los Angeles, California, United States": "0110000" }
  ],
  "Other names": [{ "81A Gloegoer Medan": "0110000" }],
  "Occupation": [
    { "Show dog": "0110000" },
    { "Singer": "1111000" },
    { "Actress": "0110000" },
    { "musician": "0111000" }
  ],
  "Years active": [{ "1982 - present": "0000000" }],
  "Partner(s)": [{ "Tony Romo (2007-2009)": "1110000" }],
  "Parent(s)": [
    { "Tadamori Oshima": "0111000" },
    { "John Lee Bottom": "0000000" }
  ],
  "Relatives": [
    { "River Phoenix (brother) ": "0000000" },
    { "Jeffrey Lynne": "0111000" },
    { "Matt Hardy (brother)": "0110000" },
    { "Summer Phoenix (sister)": "0000000" }
  ],
  "title": ["Joaquin Phoenix"]
}
