{
  "Born": [
    {
      "Camilla Rosemary Shand ,  (1947-07-17) 17 July 1947 (age 71) , King's College Hospital, London, England": "0000000"
    }
  ],
  "Spouse": [
    { "Jessica Ditzel ( m.  2009)": "0110000" },
    { "Nancy Juvonen  ( m.  2007)": "0110000" }
  ],
  "Issue": [
    { "Prince Louis of Cambridge": "1010000" },
    { "Laura Lopes": "0000000" }
  ],
  "House": [{ "Windsor (by marriage)": "1010000" }],
  "Father": [{ "Michael E. Gates": "0111000" }],
  "Mother": [{ "Robin Estanislau": "0111000" }],
  "title": ["Camilla"]
}
