{
  "Date": [
    "July 22, 1882",
    "1799 (Guyandotte)",
    "at least 5,000",
    "May 23, 1993",
    "November 15, 1630(1630-11-15) (aged 58) , Free Imperial City of Regensburg, Holy Roman Empire",
    "1 July 1981 (operational) , 29 December 1981 (official)",
    "14 November 565 (aged 83) Constantinople, Byzantine Empire",
    "11 November 1957 (1957-11-11)",
    "2010 - present",
    "c. March 1919",
    "5 September 2016  ( 2016-09-05 )  (London) ",
    "16 July 1975 (1975-07-16)",
    "May 17, 2004 (2004-05-17) (Cannes)",
    "November 29, 1988",
    "September 12, 2008",
    "November 20, 2015 (2015-11-20) (United States)",
    "30 July 1958 ( 1958-07-30 )  (age 60)  Bexleyheath, Kent, England",
    "1 November 1991",
    "May 25, 1983",
    "August 1969"
  ],
  "Ethnic groups": [
    "81.3% Maori",
    "41.1% Akan",
    "6% Lur (incl. Bakhtiari)",
    "List Javanese, Chinese, Indian, Madurese, Sundanese, Minangkabau, Batak, Banjar, Balinese, Bugis, Malay, Arabs",
    "6.7% part-Maori"
  ],
  "Person": [
    "Elaine Doyle ( m.  1959)",
    "Gustavo Alatriste",
    "Emma Thompson",
    "Douglas Booth",
    "Mountain",
    "ca.  80,000",
    "Dianne Holechek , ( m. 1958;  div. 1989) , Gena O'Kelley ,  ( m. 1998)",
    "Juri Ratas",
    "Dilip Shanghvi",
    "Nina Alu  ( m.  2008)",
    "Otto Sonnenholzner",
    "Katherine Rooney Mara",
    "Susanne Klatten",
    " Bessie Gordy (Mother)",
    "Yang Jie (Chairman)  ,  Li Yue (CEO)",
    "Michael Blake",
    "Todd Pletcher",
    "Peter Goldschmidt CEO",
    "Camon\u00e9u",
    "William Jarvis"
  ],
  "Products": [
    "Internet access",
    "Personal computers, cell phones",
    "Talent Acquisition, Talent Development, CRM, Brassring, Employee Assessments, Talent Frameworks, Watson Talent, Watson Career Coach, Watson Candidate Assistance.",
    "Broadband internet",
    "Gardasil , Singulair , Propecia/Proscar , Zocor Vioxx Fosamax Keytruda Januvia Primaxin"
  ],
  "Airlines": [
    "SilkAir",
    "Qantas",
    "Singapore Airlines",
    "Jetstar Asia Airways",
    "Scoot"
  ],
  "Genre": [
    "Hong Kong English pop",
    "electronic",
    "garage rock",
    "Pop",
    "Gothic science fiction",
    "new jack swing",
    "emo",
    "Mind sport",
    "Animation",
    " electroclash ",
    "Board game  , Chess variant",
    "Science fiction",
    "Neo Soul"
  ],
  "Location": [
    "Westwood Village Memorial Park Cemetery",
    "Northern Basque Country, France",
    "Population: 1,747,152",
    "Bandar Seri Begawan , 4.890283; 114.942217",
    "Scotland / England",
    "Springwood",
    "Ethiopia",
    "Academy Con (1965-1967) , Comic Art Convention (1968-1970)",
    "Annamoe, County Wicklow, Ireland",
    "Sweden",
    "United States of America",
    "Area : 22,142 km2 (8,549 sq mi)",
    "New Delhi",
    " France ",
    "Olympic Golf Course",
    "Hollywood, California (as Hollywood Hogan)",
    "Shakti Sthal",
    "Italy, France"
  ],
  "Fields": [
    "Electroanalytical chemistry",
    "Medicine",
    "Physical chemistry",
    "Control theory",
    "  Astronomy "
  ],
  "Money": [
    "$352.1 million",
    "US$12 million",
    "\u00a320,000,000",
    "$3.98 billion (2017)",
    "DEM180,000",
    "USD $13 million at the time of his death (approximately 1/709th of US GNP)",
    "$47,903,751",
    "$12.4 million"
  ],
  "Occupation": [
    "Actress, singer",
    "actor",
    "Actor, director, activist",
    "Physicist",
    " dancer ",
    "record executive",
    "Engineer ",
    "drummer"
  ],
  "Nationality": [
    "Canadian and American",
    "American",
    "Iranian",
    "German/British",
    "Singaporean  (since 2009)"
  ],
  "University": [
    "Thinking Machines , Walt Disney Imagineering ,  Applied Invention",
    "Moscow State University",
    "National Institutes of Health",
    "New York Law School",
    "Harvard University"
  ],
  "Companies": [
    "Norwegian Nobel Committee on behalf of the estate of Alfred Nobel",
    "Alter Ego magazine / Academy of Comic Book Arts and Sciences",
    "Playtone",
    "Jet Propulsion Laboratory",
    "Liberty Films",
    "MSFTSMusic",
    "Voltage Pictures",
    "Decca",
    "Third Worlds",
    "Polmos Lancut",
    "Bob and Beverly Lewis",
    "Duncan Family",
    "Cadbury Australia",
    "Rubyworks",
    "Philips",
    "Neon",
    "A24",
    "Nestl\u00e9",
    "PepsiCo",
    "Craig Thrupp"
  ],
  "Languages": [
    "Hindi",
    "Italian, French",
    "Russian   (used as official)",
    "Medieval Greek  (610-1453)",
    "Tigrinya"
  ],
  "Dialing code": ["1", "261", "(+62) 31", "(+62) 22"],
  "Elevation": [
    "1,312 m (4,304 ft)",
    "320 ft (98 m)",
    "11.89 m (39.01 ft)",
    "91 m (299 ft)",
    "2,250 m (7,380 ft)"
  ],
  "Height": [
    "75 in (191 cm)",
    "102 millimetres (4.0 in)",
    "Male: 85 cm",
    "5 ft 8 in (1.73 m)",
    "Height of copper statue (to torch): 151 feet 1 inch (46 meters)"
  ]
}
