{
  "Date": [
    "March 23, 1956",
    "December 1994 - May 1995",
    "February 29, 2008  (age 10)  Philippines",
    "30 July 1958 ( 1958-07-30 )  (age 60)  Bexleyheath, Kent, England",
    "1890",
    "1 July 1981 (operational) , 29 December 1981 (official)",
    "1900",
    "22 May 1978  (age 40)   Brighton, East Sussex, England",
    "Irn-Bru XS",
    "840",
    "14 April 1629 ( 1629-04-14 ) The Hague, Dutch Republic",
    "1636",
    "15 December 1990 (1990-12-15)",
    "11 November 1957 (1957-11-11)",
    "1964-present",
    "1972  ( 1972-06-12 )",
    "1985 - present",
    "David John Braben ,  (1964-01-02) 2 January 1964 (age 55) , West Bridgford, Nottingham, United Kingdom",
    "Fiery Irn-Bru",
    "2016 (2016)-present"
  ],
  "Ethnic groups": [
    "2% Turkmen and other Turkic tribes",
    "List Javanese, Chinese, Indian, Madurese, Sundanese, Minangkabau, Batak, Banjar, Balinese, Bugis, Malay, Arabs",
    "2.5% Filipino",
    "10% Kurdish",
    "6.7% part-Maori"
  ],
  "Person": [
    "Taye Diggs ( m.  2003;  div.  2014)",
    "Kim Seong-chun",
    "Lady Diana Spencer ( m.   1981 ;  div.   1996 )  ",
    "Jean Morrison",
    "Alexander Luthor",
    " Bessie Gordy (Mother)",
    "Camon\u00e9u",
    "Dilip Shanghvi",
    "ca.  80,000",
    "Hiromi Takashima",
    "Otto Sonnenholzner",
    "Asad Rehman",
    "Svatopluk Havelka",
    "Emma Thompson",
    "Lawrence Gordon",
    "Derby County Football Club",
    "Half-and-half  , Bull & terrier  ,  Fighting bull terrier ,  'Pit' bullterrier , 'Bull terrier' ,  Canis Pugilis",
    "Alvin Arcilla",
    "Paldo",
    "Ronald J. Daniels"
  ],
  "Products": [
    "peripherals",
    "Televisions",
    "Personal computers, cell phones",
    "Talent Acquisition, Talent Development, CRM, Brassring, Employee Assessments, Talent Frameworks, Watson Talent, Watson Career Coach, Watson Candidate Assistance.",
    " Black Cherry Vanilla Coca-Cola"
  ],
  "Airlines": [
    "SilkAir",
    "Qantas",
    "Singapore Airlines",
    "Jetstar Asia Airways",
    "Scoot"
  ],
  "Genre": [
    " soft rock ",
    "Gothic science fiction",
    "comedy",
    "punk rock",
    " pop ",
    "Animation",
    "Mind sport",
    "Mystery, thriller",
    "post-punk revival",
    "Alternative rock",
    "Science fiction",
    "new jack swing",
    "garage rock revival"
  ],
  "Location": [
    "Russia",
    "Calabasas, California, U.S.",
    "London and Surrey",
    "Hargeisa",
    "Great Britain",
    "Marbella, Spain",
    "South Korea",
    "Georgia",
    "Zambia",
    "Ethiopia",
    "Westwood Village Memorial Park Cemetery",
    "United Kingdom ",
    "United Kingdom, United States",
    "New Delhi",
    "Los Feliz, Los Angeles",
    "Germany",
    "Scotland / England",
    "Yes"
  ],
  "Fields": [
    "Medicine",
    " astronomy",
    "Theoretical physics",
    "  Astronomy ",
    "optics"
  ],
  "Money": [
    "$665 million (2017)",
    "$35 million",
    "$121.8 million",
    "$125 million (2016 estimate)",
    "$217 million",
    "$14 million",
    "US$300 million (2018)",
    "DEM180,000"
  ],
  "Occupation": [
    "Accountant, economist, politician",
    "Internet Entrepreneur",
    " record producer",
    "Businessman",
    "performer",
    "singer ",
    "Singer-songwriter, guitarist, producer, actor, author, talent manager",
    "Pharmacist"
  ],
  "Nationality": [
    "Hungarian  , Croatian",
    "USA",
    "French",
    "British , Italian",
    "Singaporean  (since 2009)"
  ],
  "University": [
    "Trinity College, Cambridge ",
    "Harvard University (BA) , Stanford University (JD, MBA)",
    "Mills College  (attended)",
    "Harvard University",
    "National Institutes of Health"
  ],
  "Companies": [
    "Miramax Films",
    "Monstercat",
    "Sub Pop",
    "Summit Entertainment",
    "ISAC",
    "Heathrow Airport Holdings",
    "Columbia",
    "Bacardi",
    "Charles Day Rose",
    "Mr Christian Landolt, Mr & Mrs P. Baker & Mrs D. Alder",
    "Norwegian Nobel Committee on behalf of the estate of Alfred Nobel",
    "Reprise",
    "Cinema Epoch",
    "Craig Thrupp",
    "Shinshokan",
    "Voltage Pictures",
    "Philips",
    "Murder Inc. (1997-2009, 2010-2013)",
    "Safehouse",
    "Jimmy Harry"
  ],
  "Languages": [
    "Czech",
    "Old English",
    "Tigrinya",
    "Irish",
    "Middle Chinese  (Administrative)"
  ],
  "Dialing code": ["1", "261", "(+62) 31", "(+62) 22"],
  "Elevation": [
    "1,312 m (4,304 ft)",
    "455 m (1,493 ft)",
    "620 m (2,000 ft)",
    "91 m (299 ft)",
    "200 m (700 ft)"
  ],
  "Height": [
    "175 cm (5 ft 9 in)",
    "6 ft 1 in (185 cm)",
    "5 ft 5 in (1.65 m)",
    "27 centimetres (11 in)",
    "46.4 m (152 ft)"
  ]
}
