{
  "Date": [
    "1972  ( 1972-06-12 )",
    "December 1994 - May 1995",
    "1979-1997",
    "25 July 1843(1843-07-25) (aged 76) , Glasgow, Scotland",
    "August 26, 1918  (age 100)   White Sulphur Springs, West Virginia, U.S.",
    "May 27, 1937; 81 years ago (1937-05-27)",
    "Dakota Mayi Johnson    ( 1989-10-04 )  October 4, 1989  (age 29)   Austin, Texas, U.S.",
    "October 25, 1963 (1963-10-25)  (aged 80)  Winchester, Massachusetts, United States of America",
    "June 12, 2015  ( 2015-06-12 )  (United States)",
    "1942-43",
    "June 17, 2016 (2016-06-17) (United States)",
    "22 May 1978  (age 40)   Brighton, East Sussex, England",
    "at least 5,000",
    "1995-96",
    "December 1977 - March 2004",
    "30 July 1958 ( 1958-07-30 )  (age 60)  Bexleyheath, Kent, England",
    "1962",
    "May 2, 2008 (United States)",
    "August 2011 - September 2013",
    "September 2, 2005 (2005-09-02) (Venice)"
  ],
  "Ethnic groups": [
    "6.7% part-Maori",
    "81.3% Maori",
    "10% Kurdish",
    "2% Turkmen and other Turkic tribes",
    "List Javanese, Chinese, Indian, Madurese, Sundanese, Minangkabau, Batak, Banjar, Balinese, Bugis, Malay, Arabs"
  ],
  "Person": [
    "Miguel de Leon",
    "Jeffrey Nero Hardy",
    "Gustavo Alatriste",
    "Hiromi Takashima",
    "H. Graham Motion",
    "Kathryn Walker ( m.  1985;  div.  1995)",
    "Susanne Klatten",
    "Pastor Alcover Jr.",
    "Batman",
    "Tony Chu",
    "Joanna Caroline Newsom",
    "Joseph Frank Pesci",
    "Taye Diggs ( m.  2003;  div.  2014)",
    "Malcolm Rodrigues  (CEO)",
    "Demi Moore , ( m. 1987;  div. 2000) , Emma Heming ,  ( m. 2009)",
    "Joseph Glover",
    "Jeff Richards (Managing Partner)",
    "456",
    "Michael M. Crow",
    "Robert A. Brown"
  ],
  "Products": [
    "Calvert",
    "Televisions",
    "software",
    "Royal Stag",
    " Black Cherry Vanilla Coca-Cola"
  ],
  "Airlines": [
    "SilkAir",
    "Qantas",
    "Singapore Airlines",
    "Jetstar Asia Airways",
    "Scoot"
  ],
  "Genre": [
    "Black metal",
    " pop ",
    "Various",
    "Board game ",
    "art punk",
    "  theology (later issues)",
    "punk rock",
    "experimental rock",
    "alternative rock",
    "thrash metal",
    "comedy",
    "Indie folk",
    "Board game , Abstract strategy game , Mind sport"
  ],
  "Location": [
    "Alter S\u00fcdfriedhof, Munich , 48\u00b007\u203238\u2033N 11\u00b033\u203254\u2033E\ufeff / \ufeff48.127222\u00b0N 11.565\u00b0E\ufeff / 48.127222; 11.565Coordinates: 48\u00b007\u203238\u2033N 11\u00b033\u203254\u2033E\ufeff / \ufeff48.127222\u00b0N 11.565\u00b0E\ufeff / 48.127222; 11.565",
    "Ethiopia",
    "Marbella, Spain",
    "Greece",
    "Salzburg, Austria",
    "Australia",
    "Bowie, Maryland, US",
    "Springwood",
    "Pardes Shalom Cemetery in Vaughan, Ontario, Canada",
    "United Kingdom",
    "United States of America",
    "Westwood Village Memorial Park Cemetery",
    "Switzerland",
    "Republic of the Congo",
    "United States",
    "Marlborough House, London , 51\u00b030\u203218\u2033N 0\u00b08\u20329\u2033W\ufeff / \ufeff51.50500\u00b0N 0.13583\u00b0W\ufeff / 51.50500; -0.13583",
    "3,976,000",
    "Calabasas, California, U.S."
  ],
  "Fields": [
    "Theoretical physics",
    " astronomy",
    "Control theory",
    "Electroanalytical chemistry",
    "Medicine"
  ],
  "Money": [
    "US$100 million (2014 estimate)",
    "$14 million",
    "$352.1 million",
    "$783.1 million",
    "$125 million (2016 estimate)",
    "364,455,000 SEK (2015)",
    "$32,400",
    "$3.2 million"
  ],
  "Occupation": [
    "singer ",
    "actor",
    " record producer ",
    "Ordinary Seaman",
    "comedian",
    "Pharmacist",
    "Physicist",
    "dancer"
  ],
  "Nationality": [
    "Luxembourgish",
    "Indian",
    "Canadian and American",
    "Mexican",
    "Ukrainian"
  ],
  "University": [
    " Philips Research Laboratories ",
    "University of Pennsylvania",
    "New York Law School",
    "Harvard University",
    "Harvard University (BA) , Stanford University (JD, MBA)"
  ],
  "Companies": [
    "Mr Christian Landolt, Mr & Mrs P. Baker & Mrs D. Alder",
    "Columbia",
    "Columbia, CBS",
    "Michael Jackson (1988-2005) , Center for Great Apes (2005-present)",
    "Fox Searchlight Pictures  (United States)",
    "Studio 606 West, Northridge, Los Angeles",
    "20th Century Fox ,  (International)",
    "Archie Horror",
    "RCA ",
    "Safehouse",
    "Warren A. Croll, Jr.",
    "Cinema Epoch",
    "Doc McKinney",
    "RCA Victor",
    "Fairchild Dornier",
    "Miramax Films",
    "Acid Test",
    "Various",
    "Chevrolet",
    "Ruffhouse "
  ],
  "Languages": [
    "Somali",
    "Cantonese , Shanghainese , Mandarin , Filipino , English",
    "Sidamo",
    "Russian   (used as official)",
    "English ( de facto )"
  ],
  "Dialing code": ["1", "261", "(+62) 31", "(+62) 22"],
  "Elevation": [
    "768 m (2,520 ft)",
    "200 m (700 ft)",
    "2,250 m (7,380 ft)",
    "320 ft (98 m)",
    "620 m (2,000 ft)"
  ],
  "Height": [
    "27 centimetres (11 in)",
    "Height of copper statue (to torch): 151 feet 1 inch (46 meters)",
    "75 in (191 cm)",
    "1.85 m (6 ft 1 in)",
    "108 mm (4 1/4 in.)"
  ]
}
