{
  "Capital and largest city": [{ "Torshavn": "0010000" }],
  "Official languages": [{ "Indonesian": "0111000" }, { "Korean": "1111000" }],
  "Religion": [
    { "1.4% Other (includes Baha'i, Hindu, Islam, Rastafarian)": "0010000" }
  ],
  "Demonym(s)": [{ "Iraqi": "0000000" }],
  "Government": [{ "Federal parliamentary republic": "0000000" }],
  "President ": [{ "Alassane Ouattara": "1010000" }],
  "Prime Minister ": [{ "Henry Puna": "1010000" }],
  "Speakers of the Council of Representatives ": [
    { "Dr Rebekah Widdowfield": "0111000" }
  ],
  "Chief Justice ": [{ "Medhat al-Mahmoud": "0000000" }],
  "Legislature": [{ "Parliament of Ivory Coast": "1010000" }],
  "title": ["Republic of Iraq"]
}
